inspect_requirements/__init__.py
inspect_requirements/inspect_requirements.py
inspect_requirements-0.10.7.dist-info/METADATA
inspect_requirements-0.10.7.dist-info/WHEEL
inspect_requirements-0.10.7.dist-info/entry_points.txt
inspect_requirements-0.10.7.dist-info/top_level.txt
inspect_requirements-0.10.7.dist-info/RECORD
