Metadata-Version: 2.1
Name: inspect-requirements
Version: 0.10.7
Summary: Inspect requirements.txt files of multiple repositories.
Home-page: https://github.com/Raekkeri/inspect-requirements
Download-URL: https://github.com/raekkeri/inspect-requirements/tarball/0.10.7
Author: Teemu Husso
Author-email: teemu.husso@gmail.com
License: UNKNOWN
Keywords: requirements,pip
Platform: UNKNOWN
Requires-Dist: requirements-parser (==0.5.0)
Requires-Dist: setuptools
